LICENSE
MANIFEST.in
setup.py
django_server_manager.egg-info/PKG-INFO
django_server_manager.egg-info/SOURCES.txt
django_server_manager.egg-info/dependency_links.txt
django_server_manager.egg-info/not-zip-safe
django_server_manager.egg-info/top_level.txt
server_manager/__init__.py
server_manager/admin.py
server_manager/loader.py
server_manager/models.py
server_manager/settings.py
server_manager/backends/__init__.py
server_manager/backends/base.py
server_manager/backends/mod_wsgi.py
server_manager/media/server_manager/js/server_manager.js
server_manager/templates/server_manager/changelist.html