Metadata-Version: 1.0
Name: django-server-manager
Version: 0.1.0
Summary: Django Server Manager
Home-page: http://github.com/ojii/django-server-manager
Author: Jonas Obrist
Author-email: UNKNOWN
License: UNKNOWN
Platform: UNKNOWN
